ovos_gguf_embeddings/__init__.py
ovos_gguf_embeddings/cli.py
ovos_gguf_embeddings/version.py
ovos_gguf_embeddings_plugin-0.0.0.dist-info/LICENSE
ovos_gguf_embeddings_plugin-0.0.0.dist-info/METADATA
ovos_gguf_embeddings_plugin-0.0.0.dist-info/WHEEL
ovos_gguf_embeddings_plugin-0.0.0.dist-info/entry_points.txt
ovos_gguf_embeddings_plugin-0.0.0.dist-info/top_level.txt
ovos_gguf_embeddings_plugin-0.0.0.dist-info/zip-safe
ovos_gguf_embeddings_plugin-0.0.0.dist-info/RECORD
