Metadata-Version: 2.1
Name: ovos-gguf-embeddings-plugin
Version: 0.0.0
Summary: A gguf embeddings plugin for OVOS
Home-page: https://github.com/TigreGotico/ovos-gguf-embeddings-plugin
Author: jarbasai
Author-email: jarbasai@mailfence.com
License: Apache 2.0
Keywords: OVOS openvoiceos plugin gguf recognition
Platform: UNKNOWN
Requires-Dist: ovos-plugin-manager
Requires-Dist: numpy
Requires-Dist: ovos-chromadb-embeddings-plugin
Requires-Dist: llama-cpp-python
